sendgrid_email/__init__.py
sendgrid_email-0.0.5.dist-info/METADATA
sendgrid_email-0.0.5.dist-info/WHEEL
sendgrid_email-0.0.5.dist-info/licenses/LICENSE
sendgrid_email-0.0.5.dist-info/RECORD
