Metadata-Version: 2.3
Name: sendgrid-email
Version: 0.0.5
Summary: Simple utility for sending emails via SendGrid.
Project-URL: Homepage, https://github.com/mizuki-hikaru/sendgrid-email
Project-URL: Issues, https://github.com/mizuki-hikaru/sendgrid-email/issues
Author-email: Mizuki Hikaru <mizuki@hikaru.org>
License-File: LICENSE
Classifier: License :: OSI Approved :: MIT License
Classifier: Operating System :: OS Independent
Classifier: Programming Language :: Python :: 3
Requires-Python: >=3.9
